file_manager/__init__.py
file_manager/__main__.py
file_manager/main.py
file_manager/users/__init__.py
file_manager/users/add.py
file_manager/users/delete.py
file_manager/version.py
huang_file_manager-0.1.0.dist-info/METADATA
huang_file_manager-0.1.0.dist-info/WHEEL
huang_file_manager-0.1.0.dist-info/entry_points.txt
huang_file_manager-0.1.0.dist-info/RECORD
