Metadata-Version: 2.3
Name: huang-file-manager
Version: 0.1.0
Summary: 
Author: cris
Author-email: huanghaiyss@163.com
Requires-Python: >=3.12
Classifier: Programming Language :: Python :: 3
Classifier: Programming Language :: Python :: 3.12
Classifier: Programming Language :: Python :: 3.13
Requires-Dist: typer (>=0.16.0,<0.17.0)
